sans/__init__.py
sans/__main__.py
sans/_auth.py
sans/_client.py
sans/_client.pyi
sans/_decoder.py
sans/_errors.py
sans/_eventsource.py
sans/_limiter.py
sans/_lock.py
sans/_response.py
sans/_sse.py
sans/_url.py
sans/_utils.py
sans/py.typed
sans-1.3.3.dist-info/licenses/LICENSE
sans-1.3.3.dist-info/METADATA
sans-1.3.3.dist-info/WHEEL
sans-1.3.3.dist-info/entry_points.txt
sans-1.3.3.dist-info/top_level.txt
sans-1.3.3.dist-info/RECORD
