Metadata-Version: 2.4
Name: sans
Version: 1.3.3
Summary: Synchronous / Asynchronous HTTPX extension for NationStates
Author: Zephyrkul
License: MIT License
Project-URL: homepage, https://github.com/Zephyrkul/sans
Project-URL: documentation, https://sans.readthedocs.io/en/stable/
Project-URL: repository, https://github.com/Zephyrkul/sans.git
Classifier: Development Status :: 5 - Production/Stable
Classifier: Framework :: AsyncIO
Classifier: Framework :: AnyIO
Classifier: License :: OSI Approved :: MIT License
Classifier: Intended Audience :: Developers
Classifier: Natural Language :: English
Classifier: Operating System :: OS Independent
Classifier: Programming Language :: Python :: 3 :: Only
Classifier: Programming Language :: Python :: 3.7
Classifier: Programming Language :: Python :: 3.8
Classifier: Programming Language :: Python :: 3.9
Classifier: Programming Language :: Python :: 3.10
Classifier: Programming Language :: Python :: 3.11
Classifier: Programming Language :: Python :: 3.12
Classifier: Topic :: Internet
Classifier: Topic :: Software Development :: Libraries
Classifier: Topic :: Software Development :: Libraries :: Python Modules
Classifier: Topic :: Utilities
Classifier: Typing :: Typed
Requires-Python: <4.0,>=3.7.0
License-File: LICENSE
Requires-Dist: httpx<0.29.0,>=0.24
Requires-Dist: importlib_metadata>=1.4.0; python_version < "3.8"
Provides-Extra: docs
Requires-Dist: Sphinx~=5.3; extra == "docs"
Provides-Extra: lxml
Requires-Dist: lxml~=5.0; extra == "lxml"
Provides-Extra: json
Requires-Dist: xmltodict~=0.14; extra == "json"
Dynamic: license-file
